README.md
setup.py
pyroboard/__init__.py
pyroboard/inline_keyboard.py
pyroboard/inline_pagination_keyboard.py
pyroboard/reply_keyboard.py
pyroboard.egg-info/PKG-INFO
pyroboard.egg-info/SOURCES.txt
pyroboard.egg-info/dependency_links.txt
pyroboard.egg-info/requires.txt
pyroboard.egg-info/top_level.txt