Metadata-Version: 2.1
Name: pyroboard
Version: 0.1.0
Summary: Keyboard for Pyrogram number one.
Home-page: https://github.com/pystorage/pyroboard
Author: PyMaster
Author-email: 
License: MIT
Keywords: telegram pyrogram keyboard bot userbot
Platform: UNKNOWN
Classifier: Programming Language :: Python
Classifier: Programming Language :: Python :: 3
Classifier: Programming Language :: Python :: 3.5
Classifier: Programming Language :: Python :: 3.6
Classifier: Programming Language :: Python :: 3.7
Classifier: Programming Language :: Python :: 3.8
Classifier: Topic :: Internet
Classifier: Topic :: Communications
Classifier: Topic :: Communications :: Chat
Classifier: Topic :: Software Development :: Libraries
Classifier: Topic :: Software Development :: Libraries :: Python Modules
